<?xml version="1.0" encoding="UTF-8"?><Invoice xmlns="http://rep.oio.dk/ubl/xml/schemas/0p71/pie/" xmlns:com="http://rep.oio.dk/ubl/xml/schemas/0p71/common/" xmlns:main="http://rep.oio.dk/ubl/xml/schemas/0p71/maindoc/" xmlns:xsi="http://www.w3.org/2001/XMLSchema-instance" xsi:schemaLocation="http://rep.oio.dk/ubl/xml/schemas/0p71/pie/  http://rep.oio.dk/ubl/xml/schemas/0p71/pie/piestrict.xsd"><com:ID>12034</com:ID><com:IssueDate>2013-06-07</com:IssueDate><com:TypeCode>PIE</com:TypeCode><main:InvoiceCurrencyCode>DKK</main:InvoiceCurrencyCode><com:Note><![CDATA[Job: Skiltning, Selandia Park 8, Ringsted(7855)

Blindeprikker
Prikker til alle h&#248;je vinduer i stueetage: ca. 40m. (45 ruder)
Prikker til udgangsd&#248;re p&#229; 1. Sal.: 2x62 cm. + 2x76 cm. 
Prikker til Kursuscenter d&#248;re (indvendig i gammel bygning): 2x60 cm.
Prikker rundt om vindfang ved hovedindgang: ca. 6m. (4 ruder)
Pris,&nbsp;kr. 7.000,- excl. montering
&nbsp;
1 x Automatisk d&#248;r&#229;bning folie til hovedd&#248;r&nbsp;
Pris, kr. 200,- excl. montering
&nbsp;
1 x 1-delt indgangsskilt (pylon-design) til hovedindgang (logo + sort felt) (dobbeltsidet). 
Folie p&#229; vindue. 1 x 50 cm x 50 cm. p&#229; begge sider af vinduet&nbsp;
Pris, kr.850,- excl. montering
&nbsp;
1 x stort logo (folie) p&#229; vinduer til venstre for hovedindgang: h:203 cm. x b:175 cm.
Pris, kr. 3.000,- excl. montering&#180;
&nbsp;
5 x N&#248;dudgangsskilte i folie(dobbeltsidet) 15 cm. x 15 cm. (2 stk. ved udgang, 1 stk. ved l&#230;rergang, 2 stk. p&#229; 1. Sal.)&nbsp;
Pris, kr. 750,- excl. montering
&nbsp;
2 x TOILET-hovedd&#248;re.&nbsp; 
2 x Handicap symbol-skilt p&#229; d&#248;re 15 cm. x 15 cm.(1 stk. i stuen + 1 stk. p&#229; 1. Sal).
18 x Unisex symbol-skilt p&#229; d&#248;re 15 cm. x 15 cm. (8 stk. i stuen + 8 stk. p&#229; 1. Sal + 2 stk. til l&#230;rev&#230;relse).
Pris,&nbsp;kr. 2.000,- excl. montering
&nbsp;
&nbsp;
Designopl&#230;g, opm&#229;ling, koordinering og projektstyring, opl&#230;g til logo ved hovedindgang.
Layout til: Automatisk d&#248;r&#229;bning,&nbsp; 1 x 1-delt indgangsskilt (pylon-design) til hovedindgang, 1 x stort logo (folie) p&#229; vinduer til venstre for hovedindgang,
5 x N&#248;dudgangsskilte i folie(dobbeltsidet), 2 x TOILET-hovedd&#248;re, 
2 x Handicap symbol-skilt, 18 x Unisex symbol-skilt p&#229; d&#248;re, 
klarg&#248;ring af filer til produktion, 
Pris, kr. 15.250,-

&nbsp;
&nbsp;
&nbsp;
&nbsp;
&nbsp;
&nbsp;
&nbsp;
&nbsp;
&nbsp;
&nbsp;
&nbsp;
&nbsp;
&nbsp;
&nbsp;
&nbsp;
&nbsp;
&nbsp;
&nbsp;
&nbsp;
&nbsp;
&nbsp;
&nbsp;
&nbsp;
&nbsp;
&nbsp;
&nbsp;
&nbsp;
&nbsp;
&nbsp;
&nbsp;
&nbsp;
&nbsp;
&nbsp;
&nbsp;
&nbsp;
&nbsp;
&nbsp;
&nbsp;
&nbsp;
&nbsp;
&nbsp;
Montering af alt folie + leverede skilte + egne A4 tavler samt k&#248;rsel
Pris,&nbsp;kr. 7.000,- 
]]></com:Note><com:BuyersReferenceID schemeID="EAN">5798000558199</com:BuyersReferenceID><com:ReferencedOrder><com:BuyersOrderID>7855</com:BuyersOrderID><com:IssueDate>2013-06-07</com:IssueDate></com:ReferencedOrder><com:BuyerParty><com:ID schemeID="CVR">33216769</com:ID><com:PartyName><com:Name><![CDATA[SOSU Sjælland]]></com:Name></com:PartyName><com:Address><com:ID>Fakturering</com:ID><com:Street><![CDATA[Selandia Park 6]]></com:Street><com:CityName><![CDATA[Ringsted]]></com:CityName><com:PostalZone>4100</com:PostalZone><com:Country><com:Code listID="ISO 3166-1">DK</com:Code></com:Country></com:Address><com:BuyerContact><com:ID><![CDATA[Camilla Molin]]></com:ID></com:BuyerContact></com:BuyerParty><com:SellerParty><com:ID schemeID="CVR">26881560</com:ID><com:PartyName><com:Name><![CDATA[Synergi A/S]]></com:Name></com:PartyName><com:Address><com:ID>Betaling</com:ID><com:Street><![CDATA[MARINEBUEN 11
]]></com:Street><com:CityName><![CDATA[Næstved]]></com:CityName><com:PostalZone>4700</com:PostalZone><com:Country><com:Code listID="ISO 3166-1">DK</com:Code></com:Country></com:Address><com:PartyTaxScheme><com:CompanyTaxID schemeID="CVR">26881560</com:CompanyTaxID></com:PartyTaxScheme></com:SellerParty><com:PaymentMeans><com:TypeCodeID>null</com:TypeCodeID><com:PaymentDueDate>2013-06-21</com:PaymentDueDate><com:PaymentChannelCode>KONTOOVERFØRSEL</com:PaymentChannelCode><com:PayeeFinancialAccount><com:ID>0758188337</com:ID><com:TypeCode>BANK</com:TypeCode><com:FiBranch><com:ID>2186</com:ID><com:FinancialInstitution><com:ID>null</com:ID><com:Name>Nordea</com:Name></com:FinancialInstitution></com:FiBranch></com:PayeeFinancialAccount><com:PaymentAdvice><com:AccountToAccount><com:PayerNote></com:PayerNote><com:PayeeNote></com:PayeeNote></com:AccountToAccount></com:PaymentAdvice></com:PaymentMeans><com:TaxTotal><com:TaxTypeCode>VAT</com:TaxTypeCode><com:TaxAmounts><com:TaxableAmount currencyID='DKK'>36050.00</com:TaxableAmount> <com:TaxAmount currencyID='DKK'>9012.50</com:TaxAmount></com:TaxAmounts><com:CategoryTotal><com:RateCategoryCodeID>VAT</com:RateCategoryCodeID><com:RatePercentNumeric>25</com:RatePercentNumeric><com:TaxAmounts><com:TaxableAmount currencyID='DKK'>36050.00</com:TaxableAmount><com:TaxAmount currencyID='DKK'>9012.50</com:TaxAmount></com:TaxAmounts></com:CategoryTotal></com:TaxTotal><com:LegalTotals><com:LineExtensionTotalAmount currencyID='DKK'>36050.00</com:LineExtensionTotalAmount><com:ToBePaidTotalAmount currencyID='DKK'>45062.50</com:ToBePaidTotalAmount></com:LegalTotals><com:InvoiceLine><com:ID>2</com:ID><com:InvoicedQuantity unitCode='Stk.' unitCodeListAgencyID="n/a">1.00</com:InvoicedQuantity><com:LineExtensionAmount currencyID='DKK'>36050.00</com:LineExtensionAmount><com:Item><com:ID>0</com:ID><com:Description><![CDATA[Skiltning, Selandia Park 8, Ringsted (7855)]]></com:Description></com:Item><com:BasePrice><com:PriceAmount currencyID='DKK'>36050.00</com:PriceAmount></com:BasePrice></com:InvoiceLine></Invoice>
