<?xml version="1.0" encoding="UTF-8"?><Invoice xmlns="http://rep.oio.dk/ubl/xml/schemas/0p71/pie/" xmlns:com="http://rep.oio.dk/ubl/xml/schemas/0p71/common/" xmlns:main="http://rep.oio.dk/ubl/xml/schemas/0p71/maindoc/" xmlns:xsi="http://www.w3.org/2001/XMLSchema-instance" xsi:schemaLocation="http://rep.oio.dk/ubl/xml/schemas/0p71/pie/  http://rep.oio.dk/ubl/xml/schemas/0p71/pie/piestrict.xsd"><com:ID>11833</com:ID><com:IssueDate>2013-04-10</com:IssueDate><com:TypeCode>PIE</com:TypeCode><main:InvoiceCurrencyCode>DKK</main:InvoiceCurrencyCode><com:Note><![CDATA[Job: Nyhedsbrev blå udgave(7705)
Software og funktionalitet
L&#248;sningen er&nbsp;implementeret i eksisterende Umbracol&#248;sning p&#229; http://www.sosusj.dk
&nbsp;
Strategi og struktur
Der er mulighed for, at oprette et nyhedsbrev baseret p&#229; en skabelon tilh&#248;rende kursuscenteret, hvorfra det er muligt, at v&#230;lge nyheder fra kursuscenterets nyhedsmappe.
Skabelonen er baseret p&#229; samme opbygning og funktionalitet som eksisterende SOSU nyhedsbrev, blot med et bl&#229;t layout.
Nyhedsbrevet er oprettet i samme struktur som det&nbsp;eksisterende SOSU nyhedsbrev, dog med et andet ikon, s&#229; der kan kendes forskel.
Efterf&#248;lgende funktionalitet i forhold til afsendelse, vedligeholder I igennem jeres konto hos Campaign Monitor
&nbsp;
Oprettelse af indhold
L&#248;sningen er&nbsp;leveret som en tom skabelon, hvorefter I selv skal s&#248;rge for at s&#230;tte indhold, tekst og billeder ind.
&nbsp;
Test og tilretning
Tilf&#248;jelsen er gennemg&#229;et  af Synergi og SOSU Sj&#230;lland  for eventuelle fejl og mangler inden den er&nbsp;lanceret.
Herefter er den overdraget&nbsp;og en 14 dages periode for udbedring af fejl og mangler er tr&#229;dt i kraft.


&nbsp;
&nbsp;

]]></com:Note><com:BuyersReferenceID schemeID="EAN">5798000558199</com:BuyersReferenceID><com:ReferencedOrder><com:BuyersOrderID>7705</com:BuyersOrderID><com:IssueDate>2013-04-10</com:IssueDate></com:ReferencedOrder><com:BuyerParty><com:ID schemeID="CVR">33216769</com:ID><com:PartyName><com:Name><![CDATA[SOSU Sjælland]]></com:Name></com:PartyName><com:Address><com:ID>Fakturering</com:ID><com:Street><![CDATA[Selandia Park 6]]></com:Street><com:CityName><![CDATA[Ringsted]]></com:CityName><com:PostalZone>4100</com:PostalZone><com:Country><com:Code listID="ISO 3166-1">DK</com:Code></com:Country></com:Address><com:BuyerContact><com:ID><![CDATA[Camilla Molin]]></com:ID></com:BuyerContact></com:BuyerParty><com:SellerParty><com:ID schemeID="CVR">26881560</com:ID><com:PartyName><com:Name><![CDATA[Synergi A/S]]></com:Name></com:PartyName><com:Address><com:ID>Betaling</com:ID><com:Street><![CDATA[MARINEBUEN 11
]]></com:Street><com:CityName><![CDATA[Næstved]]></com:CityName><com:PostalZone>4700</com:PostalZone><com:Country><com:Code listID="ISO 3166-1">DK</com:Code></com:Country></com:Address><com:PartyTaxScheme><com:CompanyTaxID schemeID="CVR">26881560</com:CompanyTaxID></com:PartyTaxScheme></com:SellerParty><com:PaymentMeans><com:TypeCodeID>null</com:TypeCodeID><com:PaymentDueDate>2013-04-24</com:PaymentDueDate><com:PaymentChannelCode>KONTOOVERFØRSEL</com:PaymentChannelCode><com:PayeeFinancialAccount><com:ID>0758188337</com:ID><com:TypeCode>BANK</com:TypeCode><com:FiBranch><com:ID>2186</com:ID><com:FinancialInstitution><com:ID>null</com:ID><com:Name>Nordea</com:Name></com:FinancialInstitution></com:FiBranch></com:PayeeFinancialAccount><com:PaymentAdvice><com:AccountToAccount><com:PayerNote></com:PayerNote><com:PayeeNote></com:PayeeNote></com:AccountToAccount></com:PaymentAdvice></com:PaymentMeans><com:TaxTotal><com:TaxTypeCode>VAT</com:TaxTypeCode><com:TaxAmounts><com:TaxableAmount currencyID='DKK'>4000.00</com:TaxableAmount> <com:TaxAmount currencyID='DKK'>1000.00</com:TaxAmount></com:TaxAmounts><com:CategoryTotal><com:RateCategoryCodeID>VAT</com:RateCategoryCodeID><com:RatePercentNumeric>25</com:RatePercentNumeric><com:TaxAmounts><com:TaxableAmount currencyID='DKK'>4000.00</com:TaxableAmount><com:TaxAmount currencyID='DKK'>1000.00</com:TaxAmount></com:TaxAmounts></com:CategoryTotal></com:TaxTotal><com:LegalTotals><com:LineExtensionTotalAmount currencyID='DKK'>4000.00</com:LineExtensionTotalAmount><com:ToBePaidTotalAmount currencyID='DKK'>5000.00</com:ToBePaidTotalAmount></com:LegalTotals><com:InvoiceLine><com:ID>2</com:ID><com:InvoicedQuantity unitCode='Stk.' unitCodeListAgencyID="n/a">1.00</com:InvoicedQuantity><com:LineExtensionAmount currencyID='DKK'>4000.00</com:LineExtensionAmount><com:Item><com:ID>0</com:ID><com:Description><![CDATA[Nyhedsbrev blå udgave]]></com:Description></com:Item><com:BasePrice><com:PriceAmount currencyID='DKK'>4000.00</com:PriceAmount></com:BasePrice></com:InvoiceLine></Invoice>
